pyning/__init__.py
pyning/combinationdict.py
pyning/config.py
pyning-0.1a10.dist-info/LICENSE.txt
pyning-0.1a10.dist-info/METADATA
pyning-0.1a10.dist-info/WHEEL
pyning-0.1a10.dist-info/top_level.txt
pyning-0.1a10.dist-info/RECORD
