Metadata-Version: 2.1
Name: pyning
Version: 0.1a10
Summary: A quick and extensible configuration management system
Home-page: https://github.com/essennell/pyning
Author: Steve Love
Author-email: steve@arventech.com
License: MIT
Platform: UNKNOWN
Classifier: Programming Language :: Python :: 3
Classifier: License :: OSI Approved :: MIT License
Classifier: Operating System :: OS Independent
